kakao_chatbot/__init__.py
kakao_chatbot/base.py
kakao_chatbot/context.py
kakao_chatbot/customerror.py
kakao_chatbot/event.py
kakao_chatbot/input.py
kakao_chatbot/py.typed
kakao_chatbot/response/__init__.py
kakao_chatbot/response/base.py
kakao_chatbot/response/components/__init__.py
kakao_chatbot/response/components/card.py
kakao_chatbot/response/components/common.py
kakao_chatbot/response/components/itemcard.py
kakao_chatbot/response/components/simple.py
kakao_chatbot/response/interaction.py
kakao_chatbot/utils.py
kakao_chatbot/validation.py
kakao_chatbot-0.4.3.dist-info/LICENSE
kakao_chatbot-0.4.3.dist-info/METADATA
kakao_chatbot-0.4.3.dist-info/WHEEL
kakao_chatbot-0.4.3.dist-info/RECORD
